contacts/__init__.py
contacts/contacts.py
purple_grove-0.0.1.dist-info/LICENSE.txt
purple_grove-0.0.1.dist-info/METADATA
purple_grove-0.0.1.dist-info/WHEEL
purple_grove-0.0.1.dist-info/top_level.txt
purple_grove-0.0.1.dist-info/RECORD
