Metadata-Version: 2.1
Name: purple-grove
Version: 0.0.1
Summary: Supporting library for the Purple Grove platform
Home-page: https://purplegrove.purplemonkeys.co.uk
Author: Purple Monkey Collective
Author-email: purplegrove@purplemonkeys.co.uk
Project-URL: Bug Tracker, https://github.com/PurpleMonkeyCollective/purplegrove/issues
Project-URL: Repository, https://github.com/PurpleMonkeyCollective/purplegrove
Classifier: Programming Language :: Python :: 3
Classifier: License :: OSI Approved :: MIT License
Classifier: Operating System :: OS Independent
Requires-Python: >=3.6
License-File: LICENSE.txt
